grundzeug/__init__.py
grundzeug/config/__init__.py
grundzeug/config/common.py
grundzeug/config/providers/__init__.py
grundzeug/config/providers/argparse.py
grundzeug/config/providers/common.py
grundzeug/config/providers/json.py
grundzeug/config/providers/toml.py
grundzeug/container/__init__.py
grundzeug/container/contracts.py
grundzeug/container/exceptions.py
grundzeug/container/impl.py
grundzeug/container/interface.py
grundzeug/container/mypy_plugin.py
grundzeug/container/registrations.py
grundzeug/container/utils.py
grundzeug/container/di/__init__.py
grundzeug/container/di/aliases.py
grundzeug/container/di/annotated.py
grundzeug/container/di/common.py
grundzeug/container/di/default.py
grundzeug/container/di/injection.py
grundzeug/container/plugins/ContainerAmbiguousResolutionPluginBase.py
grundzeug/container/plugins/ContainerBeanListResolutionPlugin.py
grundzeug/container/plugins/ContainerConfigurationResolutionPlugin.py
grundzeug/container/plugins/ContainerConverterResolutionPlugin.py
grundzeug/container/plugins/ContainerSingleValueResolutionPlugin.py
grundzeug/container/plugins/ContainerSpecialResolutionPlugin.py
grundzeug/container/plugins/__init__.py
grundzeug/container/plugins/common.py
grundzeug/converters/__init__.py
grundzeug/converters/common.py
grundzeug/reflection/__init__.py
grundzeug/reflection/generics.py
grundzeug/reflection/types.py
grundzeug/util/__init__.py
grundzeug/util/collections.py
grundzeug/util/docs.py
grundzeug/util/sentinels.py
grundzeug-0.1.0.dist-info/LICENSE
grundzeug-0.1.0.dist-info/METADATA
grundzeug-0.1.0.dist-info/WHEEL
grundzeug-0.1.0.dist-info/top_level.txt
grundzeug-0.1.0.dist-info/RECORD
